_nuklear.pyd
pynk/__init__.py
pynk/build.py
pynk/nkpygame.py
pynk-0.2.dist-info/DESCRIPTION.rst
pynk-0.2.dist-info/METADATA
pynk-0.2.dist-info/RECORD
pynk-0.2.dist-info/WHEEL
pynk-0.2.dist-info/dependency_links.txt
pynk-0.2.dist-info/metadata.json
pynk-0.2.dist-info/top_level.txt
