Metadata-Version: 2.0
Name: pynk
Version: 0.2
Summary: Python integration of the 'nuklear' C library.
Home-page: http://github.com/nathanrw/nuklear-cffi
Author: Nathan Woodward
Author-email: nathanrichardwoodward@gmail.com
License: Public domain
Platform: UNKNOWN
Requires-Dist: cffi (>=1.0.0)
Requires-Dist: ply (>=3.11)
